Metadata-Version: 2.1
Name: XTBApi
Version: 1.0a7
Summary: Api for XBT trading platform
Home-page: https://github.com/federico123579/XTBApi.git
Author: Federico Lolli
Author-email: federico123579@gmail.com
License: MIT
Platform: UNKNOWN
Classifier: License :: OSI Approved :: MIT License
Classifier: Programming Language :: Python
Classifier: Programming Language :: Python :: 3
Classifier: Programming Language :: Python :: 3.6
Classifier: Programming Language :: Python :: Implementation :: CPython
Classifier: Programming Language :: Python :: Implementation :: PyPy
Requires-Python: >=3.6.0
Provides-Extra: test
